example7.v
module example7(a,b,c,d,e,f,Y1,Y2);

	input a,b,c,d,e,f;
	output Y1,Y2;
	
	wire [1:3] T;
	
	not G1(T[1],b), G5(Y2,T[3]);
	or G2(T[2],c,d,e);
	nor G3(Y,a,T[2]);
	nand G4(T[3],T[1],T[2],f);
	
	endmodule
	
module example7Generator (a,b,c,d,e,f);

	output a,b,c,d,e,f;
	reg a,b,c,d,e,f;
	
	initial 
	begin
		$dumpfile("example7.vcd");
		$dumpvars;
		
		
		a=0; b=0; c=0; d=0; e=0; f=0; #10;
        a=0; b=0; c=0; d=0; e=0; f=1; #10;
        a=0; b=0; c=0; d=0; e=1; f=0; #10;
        a=0; b=0; c=0; d=0; e=1; f=1; #10;
        a=0; b=0; c=0; d=1; e=0; f=0; #10;
        a=0; b=0; c=0; d=1; e=0; f=1; #10;
        a=0; b=0; c=0; d=1; e=1; f=0; #10;
        a=0; b=0; c=0; d=1; e=1; f=1; #10;
        a=0; b=0; c=1; d=0; e=0; f=0; #10;
        a=0; b=0; c=1; d=0; e=0; f=1; #10;
        a=0; b=1; c=1; d=0; e=1; f=1; #10;
        a=1; b=0; c=1; d=1; e=0; f=1; #10;
		
		$finish;
		
		end
		endmodule
		
		
module example7TestBench;
	
	wire a,b,c,d,e,f;
	wire Y1,Y2;
	
	example7Generator GEN (a,b,c,d,e,f);
	example7 DUT (a,b,c,d,e,f,Y1,Y2);
	
	
endmodule

example7.vcd
$date
	Fri Feb 13 21:04:17 2026
$end
$version
	Icarus Verilog
$end
$timescale
	1s
$end
$scope module example7TestBench $end
$var wire 1 ! Y1 $end
$var wire 1 " f $end
$var wire 1 # e $end
$var wire 1 $ d $end
$var wire 1 % c $end
$var wire 1 & b $end
$var wire 1 ' a $end
$var wire 1 ( Y2 $end
$scope module DUT $end
$var wire 1 ) Y $end
$var wire 1 ! Y1 $end
$var wire 1 ( Y2 $end
$var wire 1 " f $end
$var wire 1 # e $end
$var wire 1 $ d $end
$var wire 1 % c $end
$var wire 1 & b $end
$var wire 1 ' a $end
$var wire 3 * T [1:3] $end
$upscope $end
$scope module GEN $end
$var reg 1 ' a $end
$var reg 1 & b $end
$var reg 1 % c $end
$var reg 1 $ d $end
$var reg 1 # e $end
$var reg 1 " f $end
$upscope $end
$upscope $end
$enddefinitions $end
$comment Show the parameter values. $end
$dumpall
$end
#0
$dumpvars
b101 *
1)
0(
0'
0&
0%
0$
0#
0"
z!
$end
#10
1"
#20
0)
b111 *
0"
1#
#30
1(
b110 *
1"
#40
0(
b111 *
0"
0#
1$
#50
1(
b110 *
1"
#60
0(
b111 *
0"
1#
#70
1(
b110 *
1"
#80
0(
b111 *
0"
0#
0$
1%
#90
1(
b110 *
1"
#100
0(
b11 *
1#
1&
#110
1(
b110 *
0#
1$
0&
1'
